gammarers/aws_waf_geo_restrict_rule/__init__.py
gammarers/aws_waf_geo_restrict_rule/py.typed
gammarers/aws_waf_geo_restrict_rule/_jsii/__init__.py
gammarers/aws_waf_geo_restrict_rule/_jsii/aws-waf-geo-restrict-rule@2.0.59.jsii.tgz
gammarers_aws_waf_geo_restrict_rule-2.0.59.dist-info/LICENSE
gammarers_aws_waf_geo_restrict_rule-2.0.59.dist-info/METADATA
gammarers_aws_waf_geo_restrict_rule-2.0.59.dist-info/WHEEL
gammarers_aws_waf_geo_restrict_rule-2.0.59.dist-info/top_level.txt
gammarers_aws_waf_geo_restrict_rule-2.0.59.dist-info/RECORD
